checkHash.py
checkHash-1.0.1.dist-info/LICENSE
checkHash-1.0.1.dist-info/METADATA
checkHash-1.0.1.dist-info/WHEEL
checkHash-1.0.1.dist-info/top_level.txt
checkHash-1.0.1.dist-info/RECORD
